[
  {"name":"هامبرغر","aliases":["برغر","همبرغر"],"cal_per_100g":260},
  {"name":"بيضة مسلوقة","aliases":["بيض مسلوق","بيضة"],"cal_per_100g":155},
  {"name":"بيتزا","aliases":["بيتزا"],"cal_per_100g":270},
  {"name":"رز مطبوخ","aliases":["رز"],"cal_per_100g":130},
  {"name":"دجاج مشوي","aliases":["دجاج"],"cal_per_100g":215},
  {"name":"سلطة خضار","aliases":["سلطة"],"cal_per_100g":40},
  {"name":"خبز عربي","aliases":["خبز","رغيف"],"cal_per_100g":300},
  {"name":"معكرونة مسلوقة","aliases":["معكرونة","مكرونة"],"cal_per_100g":110},
  {"name":"عدس مطبوخ","aliases":["عدس","شوربة عدس"],"cal_per_100g":100},
  {"name":"تفاح","aliases":["تفاحة"],"cal_per_100g":50},
  {"name":"موز","aliases":["موزة"],"cal_per_100g":100},
  {"name":"برتقال","aliases":["فاكهة برتقال"],"cal_per_100g":45},
  {"name":"ليمون","aliases":["ليمون حامض"],"cal_per_100g":30},
  {"name":"رمان","aliases":["فاكهة رمان"],"cal_per_100g":50},
  {"name":"عنب","aliases":["عنقود عنب"],"cal_per_100g":70},
  {"name":"خوخ","aliases":["خوخ"],"cal_per_100g":40},
  {"name":"كيوي","aliases":["كيوي"],"cal_per_100g":60},
  {"name":"أناناس","aliases":["فاكهة أناناس"],"cal_per_100g":50},
  {"name":"فراولة","aliases":["فراولة"],"cal_per_100g":32},
  {"name":"بطيخ","aliases":["شمام"],"cal_per_100g":30},
  {"name":"شمام","aliases":["بطيخ أبيض"],"cal_per_100g":34},
  {"name":"خيار","aliases":["خيار أخضر"],"cal_per_100g":15},
  {"name":"طماطم","aliases":["بندورة"],"cal_per_100g":18},
  {"name":"جزر","aliases":["جزرة"],"cal_per_100g":41},
  {"name":"فلفل أخضر","aliases":["فليفلة"],"cal_per_100g":20},
  {"name":"فلفل أحمر","aliases":["فليفلة حمراء"],"cal_per_100g":31},
  {"name":"باذنجان","aliases":["متة"],"cal_per_100g":25},
  {"name":"كوسا","aliases":["كوسا خضراء"],"cal_per_100g":20},
  {"name":"بطاطا","aliases":["بطاطس"],"cal_per_100g":77},
  {"name":"ثوم","aliases":["ثومة"],"cal_per_100g":149},
  {"name":"بصل","aliases":["بصلة"],"cal_per_100g":40},
  {"name":"كرفس","aliases":["كرافس"],"cal_per_100g":16},
  {"name":"سبانخ","aliases":["سلق"],"cal_per_100g":23},
  {"name":"جرجير","aliases":["سلطة جرجير"],"cal_per_100g":25},
  {"name":"ملفوف","aliases":["كرنب"],"cal_per_100g":27},
  {"name":"فاصولياء خضراء","aliases":["لوبيا"],"cal_per_100g":31},
  {"name":"حمص","aliases":["حمص مسلوق"],"cal_per_100g":160},
  {"name":"عدس","aliases":["شوربة عدس"],"cal_per_100g":100},
  {"name":"كاري دجاج","aliases":["دجاج بالكاري"],"cal_per_100g":240},
  {"name":"كباب لحم","aliases":["كباب"],"cal_per_100g":250},
  {"name":"شاورما دجاج","aliases":["شاورما"],"cal_per_100g":290},
  {"name":"فلافل","aliases":["فلافل مقلي"],"cal_per_100g":330},
  {"name":"محشي ورق عنب","aliases":["ورق عنب"],"cal_per_100g":140},
  {"name":"محشي كوسا","aliases":["كوسا محشي"],"cal_per_100g":150},
  {"name":"مقلوبة","aliases":["رز وخضار"],"cal_per_100g":220},
  {"name":"مسخن","aliases":["دجاج مسخن"],"cal_per_100g":300},
  {"name":"كفتة","aliases":["كفتة لحم"],"cal_per_100g":220},
  {"name":"بيتزا لبنانية","aliases":["بيتزا"],"cal_per_100g":280},
  {"name":"مجدرة","aliases":["عدس وأرز"],"cal_per_100g":220},
  {"name":"لحم مشوي","aliases":["لحم"],"cal_per_100g":260},
  {"name":"لحم بعجين","aliases":["عجين باللحم"],"cal_per_100g":300},
  {"name":"فطيرة جبنة","aliases":["جبنة"],"cal_per_100g":260},
  {"name":"فطيرة سبانخ","aliases":["سبانخ"],"cal_per_100g":220},
  {"name":"قطايف","aliases":["حلويات"],"cal_per_100g":420},
  {"name":"كنافة","aliases":["حلويات"],"cal_per_100g":410},
  {"name":"بقلاوة","aliases":["حلويات"],"cal_per_100g":430},
  {"name":"معمول","aliases":["حلويات"],"cal_per_100g":400},
  {"name":"جلاش","aliases":["حلويات"],"cal_per_100g":400},
  {"name":"شوكولاتة بالحليب","aliases":["شوكولاتة","كاكاو"],"cal_per_100g":530},
  {"name":"عصير برتقال","aliases":["برتقال"],"cal_per_100g":45},
  {"name":"عصير تفاح","aliases":["تفاح"],"cal_per_100g":50},
  {"name":"عصير ليمون","aliases":["ليمون"],"cal_per_100g":30},
  {"name":"عصير رمان","aliases":["رمان"],"cal_per_100g":50},
  {"name":"عصير مشكل","aliases":["فاكهة"],"cal_per_100g":55},
  {"name":"مشروب كوكاكولا","aliases":["كوكا كولا","cola"],"cal_per_100g":42},
  {"name":"مشروب بيبسي","aliases":["Pepsi"],"cal_per_100g":42},
  {"name":"مشروب سفن أب","aliases":["7up"],"cal_per_100g":38},
  {"name":"مشروب ميرندا برتقال","aliases":["Mirinda"],"cal_per_100g":45},
  {"name":"قهوة عربية","aliases":["قهوة"],"cal_per_100g":2},
  {"name":"قهوة تركية","aliases":["قهوة"],"cal_per_100g":2},
  {"name":"شاي أحمر","aliases":["شاي"],"cal_per_100g":2},
  {"name":"شاي أخضر","aliases":["Green Tea"],"cal_per_100g":1},
  {"name":"شاي نعناع","aliases":["نعناع"],"cal_per_100g":1},
  {"name":"حليب كامل الدسم","aliases":["حليب"],"cal_per_100g":65},
  {"name":"لبن رايب","aliases":["لبن"],"cal_per_100g":60},
  {"name":"لبنة","aliases":["زبادي"],"cal_per_100g":110},
  {"name":"فريكة","aliases":["رز فريكة"],"cal_per_100g":150},
  {"name":"ساندويتش جبنة","aliases":["جبنة"],"cal_per_100g":260},
  {"name":"ساندويتش شاورما لحم","aliases":["شاورما"],"cal_per_100g":300},
  {"name":"ساندويتش فلافل","aliases":["فلافل"],"cal_per_100g":330},
  {"name":"مقبلات مشكّلة","aliases":["مقبلات"],"cal_per_100g":200},
  {"name":"سلطة فتوش","aliases":["فتوش"],"cal_per_100g":80},
  {"name":"سلطة تبولة","aliases":["تبولة"],"cal_per_100g":60},
  {"name":"سلطة بابا غنوج","aliases":["بابا غنوج"],"cal_per_100g":120},
  {"name":"سلطة خيار وطماطم","aliases":["سلطة"],"cal_per_100g":30},
  {"name":"سلطة جرجير","aliases":["جرجير"],"cal_per_100g":25},
  {"name":"سلطة جزر","aliases":["جزر"],"cal_per_100g":40},
  {"name":"سلطة ملفوف","aliases":["ملفوف"],"cal_per_100g":30},
  {"name":"نوتيلا","aliases":["Nutella","شوكولاتة البندق"],"cal_per_100g":530},
  {"name":"كيندر بوينو","aliases":["Kinder Bueno"],"cal_per_100g":550},
  {"name":"شوكولاتة ميلكا","aliases":["Milka"],"cal_per_100g":540},
  {"name":"شوكولاتة تويكس","aliases":["Twix"],"cal_per_100g":500},
  {"name":"شوكولاتة سنكرز","aliases":["Snickers"],"cal_per_100g":488},
  {"name":"شوكولاتة مارس","aliases":["Mars"],"cal_per_100g":475},
  {"name":"شوكولاتة دوريتوس","aliases":["Doritos Choco"],"cal_per_100g":520},
  {"name":"شوكولاتة كادبوري","aliases":["Cadbury"],"cal_per_100g":545},
  {"name":"شوكولاتة هيرشي","aliases":["Hershey"],"cal_per_100g":500},
  {"name":"ريسيز","aliases":["Reese's","فستق شوكولاتة"],"cal_per_100g":530}
]
